tree_sitter_javadoc/__init__.py
tree_sitter_javadoc/__init__.pyi
tree_sitter_javadoc/_binding.abi3.so
tree_sitter_javadoc/binding.c
tree_sitter_javadoc/py.typed
tree_sitter_javadoc/queries/highlights.scm
tree_sitter_javadoc/queries/injections.scm
tree_sitter_javadoc-0.2.4.dist-info/METADATA
tree_sitter_javadoc-0.2.4.dist-info/WHEEL
tree_sitter_javadoc-0.2.4.dist-info/top_level.txt
tree_sitter_javadoc-0.2.4.dist-info/RECORD
tree_sitter_javadoc-0.2.4.dist-info/licenses/LICENSE
