Metadata-Version: 2.4
Name: tree-sitter-javadoc
Version: 0.2.4
Summary: Parser for Javadoc documentation comments
Author-email: Robert Muir <rmuir@apache.org>
License: MIT
Project-URL: Homepage, https://github.com/rmuir/tree-sitter-javadoc
Keywords: incremental,parsing,tree-sitter,javadoc
Classifier: Intended Audience :: Developers
Classifier: Topic :: Software Development :: Compilers
Classifier: Topic :: Text Processing :: Linguistic
Classifier: Typing :: Typed
Requires-Python: >=3.10
License-File: LICENSE
Provides-Extra: core
Requires-Dist: tree-sitter~=0.25; extra == "core"
Dynamic: license-file
